examples/__init__.py
examples/approve_tasks_in_bulk.py
examples/get_api_definition.py
examples/mass_approve_tasks.py
examples/rerun_pending_tasks.py
examples/trigger_and_poll_tasks.py
examples/trigger_templated_tasks.py
relevanceai/__init__.py
relevanceai/_base_client.py
relevanceai/_client.py
relevanceai/_resource.py
relevanceai/resources/__init__.py
relevanceai/resources/agent.py
relevanceai/resources/agents.py
relevanceai/resources/knowledge.py
relevanceai/resources/tasks.py
relevanceai/resources/tool.py
relevanceai/resources/tools.py
relevanceai/types/__init__.py
relevanceai/types/agent.py
relevanceai/types/knowledge.py
relevanceai/types/params.py
relevanceai/types/task.py
relevanceai/types/tool.py
relevanceai/types/transformations.py
tests/__init__.py
tests/test_client.py
tests/resources/__init__.py
tests/resources/test_agent.py
tests/resources/test_agents.py
tests/resources/test_tasks.py
tests/resources/test_tool.py
tests/resources/test_tools.py
relevanceai-10.2.0.dist-info/LICENSE
relevanceai-10.2.0.dist-info/METADATA
relevanceai-10.2.0.dist-info/WHEEL
relevanceai-10.2.0.dist-info/top_level.txt
relevanceai-10.2.0.dist-info/RECORD
