Metadata-Version: 2.1
Name: relevanceai
Version: 10.2.0
Home-page: https://relevanceai.com/
Author: Relevance AI
Author-email: jacky@relevanceai.com
License-File: LICENSE
Requires-Dist: pydantic==2.8.2
Requires-Dist: requests==2.32.3
Requires-Dist: httpx==0.27.2
Requires-Dist: pytest==8.3.4
